yowasp_nextpnr_ecp5/__init__.py
yowasp_nextpnr_ecp5/ecpbram.wasm
yowasp_nextpnr_ecp5/ecpmulti.wasm
yowasp_nextpnr_ecp5/ecppack.wasm
yowasp_nextpnr_ecp5/ecppll.wasm
yowasp_nextpnr_ecp5/ecpunpack.wasm
yowasp_nextpnr_ecp5/nextpnr-ecp5.wasm
yowasp_nextpnr_ecp5/share/ecp5/chipdb-25k.bin
yowasp_nextpnr_ecp5/share/ecp5/chipdb-45k.bin
yowasp_nextpnr_ecp5/share/ecp5/chipdb-85k.bin
yowasp_nextpnr_ecp5/share/trellis/database/devices.json
yowasp_nextpnr_ecp5/share/trellis/database/ECP5/LFE5U-12F/globals.json
yowasp_nextpnr_ecp5/share/trellis/database/ECP5/LFE5U-12F/iodb.json
yowasp_nextpnr_ecp5/share/trellis/database/ECP5/LFE5U-12F/tilegrid.json
yowasp_nextpnr_ecp5/share/trellis/database/ECP5/LFE5U-25F/globals.json
yowasp_nextpnr_ecp5/share/trellis/database/ECP5/LFE5U-25F/iodb.json
yowasp_nextpnr_ecp5/share/trellis/database/ECP5/LFE5U-25F/tilegrid.json
yowasp_nextpnr_ecp5/share/trellis/database/ECP5/LFE5U-45F/globals.json
yowasp_nextpnr_ecp5/share/trellis/database/ECP5/LFE5U-45F/iodb.json
yowasp_nextpnr_ecp5/share/trellis/database/ECP5/LFE5U-45F/tilegrid.json
yowasp_nextpnr_ecp5/share/trellis/database/ECP5/LFE5U-85F/globals.json
yowasp_nextpnr_ecp5/share/trellis/database/ECP5/LFE5U-85F/iodb.json
yowasp_nextpnr_ecp5/share/trellis/database/ECP5/LFE5U-85F/tilegrid.json
yowasp_nextpnr_ecp5/share/trellis/database/ECP5/LFE5UM-25F/globals.json
yowasp_nextpnr_ecp5/share/trellis/database/ECP5/LFE5UM-25F/iodb.json
yowasp_nextpnr_ecp5/share/trellis/database/ECP5/LFE5UM-25F/tilegrid.json
yowasp_nextpnr_ecp5/share/trellis/database/ECP5/LFE5UM-45F/globals.json
yowasp_nextpnr_ecp5/share/trellis/database/ECP5/LFE5UM-45F/iodb.json
yowasp_nextpnr_ecp5/share/trellis/database/ECP5/LFE5UM-45F/tilegrid.json
yowasp_nextpnr_ecp5/share/trellis/database/ECP5/LFE5UM-85F/globals.json
yowasp_nextpnr_ecp5/share/trellis/database/ECP5/LFE5UM-85F/iodb.json
yowasp_nextpnr_ecp5/share/trellis/database/ECP5/LFE5UM-85F/tilegrid.json
yowasp_nextpnr_ecp5/share/trellis/database/ECP5/LFE5UM5G-25F/globals.json
yowasp_nextpnr_ecp5-0.9.0.0.post686.dist-info/METADATA
yowasp_nextpnr_ecp5-0.9.0.0.post686.dist-info/WHEEL
yowasp_nextpnr_ecp5-0.9.0.0.post686.dist-info/entry_points.txt
yowasp_nextpnr_ecp5-0.9.0.0.post686.dist-info/top_level.txt
yowasp_nextpnr_ecp5-0.9.0.0.post686.dist-info/RECORD
