Metadata-Version: 2.4
Name: yowasp-nextpnr-ecp5
Version: 0.9.0.0.post686
Summary: nextpnr-ecp5 FPGA place and route tool
Author-email: Catherine <whitequark@whitequark.org>
License-Expression: ISC
Project-URL: Homepage, https://yowasp.org/
Project-URL: Source Code, https://github.com/YoWASP/nextpnr
Project-URL: Bug Tracker, https://github.com/YoWASP/nextpnr/issues
Requires-Dist: yowasp-runtime~=1.1
